LICENSE
README.md
setup.py
tap_slack/__init__.py
tap_slack/catalog.py
tap_slack/client.py
tap_slack/streams.py
tap_slack/transform.py
tap_slack.egg-info/PKG-INFO
tap_slack.egg-info/SOURCES.txt
tap_slack.egg-info/dependency_links.txt
tap_slack.egg-info/entry_points.txt
tap_slack.egg-info/requires.txt
tap_slack.egg-info/top_level.txt
tap_slack/schemas/channel_members.json
tap_slack/schemas/channels.json
tap_slack/schemas/files.json
tap_slack/schemas/messages.json
tap_slack/schemas/remote_files.json
tap_slack/schemas/teams.json
tap_slack/schemas/threads.json
tap_slack/schemas/user_groups.json
tap_slack/schemas/users.json
tests/__init__.py
tests/test_configuration.py
tests/test_sync.py